toolforge_i18n/__init__.py
toolforge_i18n/_flask.py
toolforge_i18n/_formatters.py
toolforge_i18n/_get_gender.py
toolforge_i18n/_language_info.py
toolforge_i18n/_pytest_plugin.py
toolforge_i18n/_translations.py
toolforge_i18n/_translations_checks.py
toolforge_i18n/_user_agent.py
toolforge_i18n/py.typed
toolforge_i18n-0.1.2.dist-info/METADATA
toolforge_i18n-0.1.2.dist-info/WHEEL
toolforge_i18n-0.1.2.dist-info/entry_points.txt
toolforge_i18n-0.1.2.dist-info/licenses/LICENSE
toolforge_i18n-0.1.2.dist-info/RECORD
