Metadata-Version: 2.4
Name: toolforge-i18n
Version: 0.1.2
Summary: A library for making Toolforge tools written in Python translatable.
Project-URL: Documentation, https://toolforge-i18n.readthedocs.io/en/latest/
Project-URL: Issues, https://phabricator.wikimedia.org/tag/toolforge_i18n/
Project-URL: Source, https://gitlab.wikimedia.org/lucaswerkmeister/toolforge_i18n/
Author-email: Lucas Werkmeister <mail@lucaswerkmeister.de>
License-Expression: BSD-3-Clause
License-File: LICENSE
Keywords: i18n,toolforge,translation,wikimedia
Classifier: Development Status :: 3 - Alpha
Classifier: Intended Audience :: Developers
Classifier: License :: OSI Approved :: BSD License
Classifier: Programming Language :: Python
Classifier: Programming Language :: Python :: 3.11
Classifier: Programming Language :: Python :: 3.12
Classifier: Topic :: Software Development :: Internationalization
Classifier: Topic :: Software Development :: Libraries
Classifier: Topic :: Software Development :: Localization
Requires-Python: >=3.11
Requires-Dist: babel
Requires-Dist: beautifulsoup4
Requires-Dist: mwapi
Requires-Dist: requests
Provides-Extra: flask
Requires-Dist: flask; extra == 'flask'
Requires-Dist: markupsafe; extra == 'flask'
Requires-Dist: werkzeug; extra == 'flask'
